<routes>
    <trip id="passenger38" type="passenger" depart="0.75" departSpeed="max" from="edge_3_2" to="-323130964"/>
    <trip id="passenger39" type="passenger" depart="1.62" departSpeed="max" from="edge_3_2" to="-323130964"/>
    <trip id="passenger40" type="passenger" depart="4.57" departSpeed="max" from="edge_3_2" to="-323130964"/>
    <trip id="passenger41" type="passenger" depart="7.88" departSpeed="max" from="edge_3_2" to="-323130964"/>
    <trip id="passenger42" type="passenger" depart="13.91" departSpeed="max" from="edge_3_2" to="-323130964"/>
    <trip id="passenger1" type="passenger" depart="13.93" departSpeed="max" from="6717304528" to="edge_3_1"/>
    <trip id="passenger2" type="passenger" depart="21.59" departSpeed="max" from="6717304528" to="edge_3_1"/>
    <trip id="passenger3" type="passenger" depart="25.72" departSpeed="max" from="6717304528" to="edge_3_1"/>
    <trip id="passenger4" type="passenger" depart="28.59" departSpeed="max" from="6717304528" to="edge_3_1"/>
    <trip id="passenger5" type="passenger" depart="34.73" departSpeed="max" from="6717304528" to="edge_3_1"/>
    <trip id="passenger94" type="passenger" depart="37.25" departSpeed="max" from="-6717304529" to="edge_3_1"/>
    <trip id="passenger43" type="passenger" depart="38.92" departSpeed="max" from="edge_3_2" to="edge_2_2"/>
    <trip id="passenger44" type="passenger" depart="42.62" departSpeed="max" from="edge_3_2" to="-323130964"/>
    <trip id="passenger100" type="passenger" depart="45.10" departSpeed="max" from="edge_19_1" to="edge_3_1"/>
    <trip id="passenger45" type="passenger" depart="46.13" departSpeed="max" from="edge_3_2" to="-323130964"/>
    <trip id="passenger46" type="passenger" depart="47.27" departSpeed="max" from="edge_3_2" to="-323130964"/>
    <trip id="passenger47" type="passenger" depart="47.35" departSpeed="max" from="edge_3_2" to="-323130964"/>
    <trip id="passenger48" type="passenger" depart="50.11" departSpeed="max" from="edge_3_2" to="-323130964"/>
    <trip id="passenger6" type="passenger" depart="50.94" departSpeed="max" from="6717304528" to="edge_3_1"/>
    <trip id="passenger7" type="passenger" depart="54.05" departSpeed="max" from="6717304528" to="edge_3_1"/>
    <trip id="passenger49" type="passenger" depart="62.42" departSpeed="max" from="edge_3_2" to="-323130964"/>
    <trip id="passenger8" type="passenger" depart="62.44" departSpeed="max" from="6717304528" to="edge_3_1"/>
    <trip id="passenger50" type="passenger" depart="67.33" departSpeed="max" from="edge_3_2" to="-323130964"/>
    <trip id="passenger51" type="passenger" depart="69.75" departSpeed="max" from="edge_3_2" to="-323130964"/>
    <trip id="passenger52" type="passenger" depart="73.76" departSpeed="max" from="edge_3_2" to="-323130964"/>
    <trip id="passenger53" type="passenger" depart="75.66" departSpeed="max" from="edge_3_2" to="-323130964"/>
    <trip id="passenger54" type="passenger" depart="77.52" departSpeed="max" from="edge_3_2" to="-323130964"/>
    <trip id="passenger55" type="passenger" depart="86.28" departSpeed="max" from="edge_3_2" to="-323130964"/>
    <trip id="delivery91" type="delivery" depart="88.20" departSpeed="max" from="edge_3_2" to="-323130964"/>
    <trip id="passenger9" type="passenger" depart="89.39" departSpeed="max" from="6717304528" to="edge_3_1"/>
    <trip id="passenger56" type="passenger" depart="90.77" departSpeed="max" from="edge_3_2" to="-323130964"/>
    <trip id="passenger57" type="passenger" depart="105.20" departSpeed="max" from="edge_3_2" to="-323130964"/>
    <trip id="passenger58" type="passenger" depart="124.17" departSpeed="max" from="edge_3_2" to="-323130964"/>
    <trip id="passenger95" type="passenger" depart="126.39" departSpeed="max" from="-6717304529" to="-323130964"/>
    <trip id="passenger10" type="passenger" depart="132.66" departSpeed="max" from="6717304528" to="edge_3_1"/>
    <trip id="passenger11" type="passenger" depart="140.97" departSpeed="max" from="6717304528" to="edge_3_1"/>
    <trip id="passenger59" type="passenger" depart="143.91" departSpeed="max" from="edge_3_2" to="-323130964"/>
    <trip id="passenger60" type="passenger" depart="144.37" departSpeed="max" from="edge_3_2" to="-323130964"/>
    <trip id="passenger12" type="passenger" depart="157.45" departSpeed="max" from="6717304528" to="edge_3_1"/>
    <trip id="passenger61" type="passenger" depart="170.69" departSpeed="max" from="edge_3_2" to="-323130964"/>
    <trip id="passenger13" type="passenger" depart="173.82" departSpeed="max" from="6717304528" to="edge_3_1"/>
    <trip id="passenger14" type="passenger" depart="179.94" departSpeed="max" from="6717304528" to="edge_3_1"/>
    <trip id="passenger62" type="passenger" depart="180.99" departSpeed="max" from="edge_3_2" to="-323130964"/>
    <trip id="passenger15" type="passenger" depart="184.52" departSpeed="max" from="6717304528" to="edge_3_1"/>
    <trip id="passenger63" type="passenger" depart="190.20" departSpeed="max" from="edge_3_2" to="-323130964"/>
    <trip id="passenger64" type="passenger" depart="191.34" departSpeed="max" from="edge_3_2" to="-323130964"/>
    <trip id="passenger16" type="passenger" depart="194.20" departSpeed="max" from="6717304528" to="edge_3_1"/>
    <trip id="passenger65" type="passenger" depart="201.79" departSpeed="max" from="edge_3_2" to="-323130964"/>
    <trip id="passenger66" type="passenger" depart="203.28" departSpeed="max" from="edge_3_2" to="-323130964"/>
    <trip id="passenger67" type="passenger" depart="211.10" departSpeed="max" from="edge_3_2" to="-323130964"/>
    <trip id="passenger17" type="passenger" depart="223.33" departSpeed="max" from="6717304528" to="edge_3_1"/>
    <trip id="passenger18" type="passenger" depart="236.90" departSpeed="max" from="6717304528" to="edge_3_1"/>
    <trip id="passenger19" type="passenger" depart="237.09" departSpeed="max" from="6717304528" to="edge_3_1"/>
    <trip id="passenger68" type="passenger" depart="251.47" departSpeed="max" from="edge_3_2" to="-323130964"/>
    <trip id="passenger20" type="passenger" depart="255.81" departSpeed="max" from="6717304528" to="edge_3_1"/>
    <trip id="passenger69" type="passenger" depart="258.05" departSpeed="max" from="edge_3_2" to="-323130964"/>
    <trip id="passenger21" type="passenger" depart="264.52" departSpeed="max" from="6717304528" to="edge_3_1"/>
    <trip id="bicycle98" type="bicycle" depart="268.91" departSpeed="max" from="-6717304529" to="edge_3_1"/>
    <trip id="passenger70" type="passenger" depart="269.30" departSpeed="max" from="edge_3_2" to="-323130964"/>
    <trip id="passenger22" type="passenger" depart="273.00" departSpeed="max" from="6717304528" to="edge_3_1"/>
    <trip id="passenger96" type="passenger" depart="282.52" departSpeed="max" from="-6717304529" to="edge_3_1"/>
    <trip id="passenger71" type="passenger" depart="288.82" departSpeed="max" from="edge_3_2" to="-323130964"/>
    <trip id="passenger72" type="passenger" depart="291.86" departSpeed="max" from="edge_3_2" to="-323130964"/>
    <trip id="passenger23" type="passenger" depart="296.42" departSpeed="max" from="6717304528" to="edge_3_1"/>
    <trip id="passenger24" type="passenger" depart="304.76" departSpeed="max" from="6717304528" to="edge_3_1"/>
    <trip id="passenger73" type="passenger" depart="316.36" departSpeed="max" from="edge_3_2" to="-323130964"/>
    <trip id="passenger74" type="passenger" depart="344.12" departSpeed="max" from="edge_3_2" to="-323130964"/>
    <trip id="truck101" type="truck" depart="346.34" departSpeed="max" from="edge_19_1" to="edge_3_1"/>
    <trip id="delivery92" type="delivery" depart="354.76" departSpeed="max" from="edge_3_2" to="-323130964"/>
    <trip id="passenger75" type="passenger" depart="357.06" departSpeed="max" from="edge_3_2" to="-323130964"/>
    <trip id="delivery93" type="delivery" depart="361.26" departSpeed="max" from="edge_3_2" to="-323130964"/>
    <trip id="passenger25" type="passenger" depart="369.40" departSpeed="max" from="6717304528" to="edge_2_2"/>
    <trip id="delivery37" type="delivery" depart="374.57" departSpeed="max" from="6717304528" to="edge_3_1"/>
    <trip id="passenger26" type="passenger" depart="376.66" departSpeed="max" from="6717304528" to="edge_3_1"/>
    <trip id="passenger76" type="passenger" depart="398.78" departSpeed="max" from="edge_3_2" to="-323130964"/>
    <trip id="passenger27" type="passenger" depart="403.54" departSpeed="max" from="6717304528" to="edge_3_1"/>
    <trip id="delivery99" type="delivery" depart="418.32" departSpeed="max" from="-6717304529" to="-323130964"/>
    <trip id="passenger77" type="passenger" depart="422.92" departSpeed="max" from="edge_3_2" to="-323130964"/>
    <trip id="passenger78" type="passenger" depart="425.92" departSpeed="max" from="edge_3_2" to="-323130964"/>
    <trip id="passenger79" type="passenger" depart="428.90" departSpeed="max" from="edge_3_2" to="-323130964"/>
    <trip id="passenger80" type="passenger" depart="434.10" departSpeed="max" from="edge_3_2" to="-323130964"/>
    <trip id="passenger28" type="passenger" depart="447.43" departSpeed="max" from="6717304528" to="edge_3_1"/>
    <trip id="passenger81" type="passenger" depart="470.23" departSpeed="max" from="edge_3_2" to="-323130964"/>
    <trip id="passenger82" type="passenger" depart="472.55" departSpeed="max" from="edge_3_2" to="-323130964"/>
    <trip id="passenger29" type="passenger" depart="481.26" departSpeed="max" from="6717304528" to="edge_3_1"/>
    <trip id="passenger83" type="passenger" depart="492.71" departSpeed="max" from="edge_3_2" to="-323130964"/>
    <trip id="bus97" type="bus" depart="506.68" departSpeed="max" from="-6717304529" to="-323130964"/>
    <trip id="passenger84" type="passenger" depart="508.53" departSpeed="max" from="edge_3_2" to="-323130964"/>
    <trip id="passenger85" type="passenger" depart="508.68" departSpeed="max" from="edge_3_2" to="-323130964"/>
    <trip id="passenger30" type="passenger" depart="517.55" departSpeed="max" from="6717304528" to="edge_3_1"/>
    <trip id="passenger31" type="passenger" depart="520.25" departSpeed="max" from="6717304528" to="edge_3_1"/>
    <trip id="passenger86" type="passenger" depart="526.06" departSpeed="max" from="edge_3_2" to="-323130964"/>
    <trip id="passenger32" type="passenger" depart="544.63" departSpeed="max" from="6717304528" to="edge_3_1"/>
    <trip id="passenger33" type="passenger" depart="547.63" departSpeed="max" from="6717304528" to="edge_3_1"/>
    <trip id="passenger87" type="passenger" depart="565.62" departSpeed="max" from="edge_3_2" to="-323130964"/>
    <trip id="passenger34" type="passenger" depart="578.06" departSpeed="max" from="6717304528" to="edge_3_1"/>
    <trip id="passenger88" type="passenger" depart="587.24" departSpeed="max" from="edge_3_2" to="-323130964"/>
    <trip id="passenger35" type="passenger" depart="587.40" departSpeed="max" from="6717304528" to="edge_3_1"/>
    <trip id="passenger36" type="passenger" depart="594.32" departSpeed="max" from="6717304528" to="edge_3_1"/>
    <trip id="passenger89" type="passenger" depart="598.81" departSpeed="max" from="edge_3_2" to="-323130964"/>
    <trip id="passenger90" type="passenger" depart="599.16" departSpeed="max" from="edge_3_2" to="-323130964"/>
</routes>
